DekuDealsAPI/__init__.py
DekuDealsAPI/page.py
DekuDealsAPI/search.py
dekudealsapi-0.1.1.dist-info/METADATA
dekudealsapi-0.1.1.dist-info/WHEEL
dekudealsapi-0.1.1.dist-info/licenses/LICENSE
dekudealsapi-0.1.1.dist-info/RECORD
