Metadata-Version: 2.1
Name: DekuDealsAPI
Version: 0.1.1
Summary: Python3 API for DekuDeals
Project-URL: Homepage, https://github.com/randomcoder67/DekuDealsAPI
Project-URL: Bug Tracker, https://github.com/randomcoder67/DekuDealsAPI/issues
Author-email: randomcoder67 <author@example.com>
License-File: LICENSE
